{
	"ulid": "01EYG3P1MGHBRF8YZ7H7WX75K1",
	"minTime": 1613203200000,
	"maxTime": 1613260800000,
	"stats": {
		"numSamples": 20,
		"numSeries": 5,
		"numChunks": 10
	},
	"compaction": {
		"level": 2,
		"sources": [
			"01EYES36Q1MP6R7QTZ8A5PEY2X",
			"01EYFQ1W40SBGCWEFX1VXVK8BV"
		],
		"parents": [
			{
				"ulid": "01EYES36Q1MP6R7QTZ8A5PEY2X",
				"minTime": 1613203200000,
				"maxTime": 1613210400000
			},
			{
				"ulid": "01EYFQ1W40SBGCWEFX1VXVK8BV",
				"minTime": 1613253600000,
				"maxTime": 1613260800000
			}
		]
	},
	"version": 1
}